collective.MockMailHost-3.0.0-py3.11-nspkg.pth
collective/MockMailHost/MailHost_icon.gif
collective/MockMailHost/MockMailHost.py
collective/MockMailHost/__init__.py
collective/MockMailHost/config.py
collective/MockMailHost/configure.zcml
collective/MockMailHost/setuphandlers.py
collective/MockMailHost/testing.py
collective/MockMailHost/version.txt
collective/MockMailHost/browser/__init__.py
collective/MockMailHost/browser/configure.zcml
collective/MockMailHost/browser/views.py
collective/MockMailHost/profiles/default/import_steps.xml
collective/MockMailHost/profiles/default/mockmailhost_various.txt
collective/MockMailHost/profiles/default/toolset.xml
collective/MockMailHost/tests/SendEmail.txt
collective/MockMailHost/tests/__init__.py
collective/MockMailHost/tests/testFunctional.py
collective.MockMailHost-3.0.0.dist-info/METADATA
collective.MockMailHost-3.0.0.dist-info/WHEEL
collective.MockMailHost-3.0.0.dist-info/entry_points.txt
collective.MockMailHost-3.0.0.dist-info/namespace_packages.txt
collective.MockMailHost-3.0.0.dist-info/top_level.txt
collective.MockMailHost-3.0.0.dist-info/RECORD
