Metadata-Version: 2.1
Name: collective.MockMailHost
Version: 3.0.0
Summary: Used for integration testing with Plone
Home-page: https://github.com/collective/collective.mockmailhost
Author: Suresh V.
Author-email: suresh@grafware.com
License: GPL
Keywords: mock mailhost tests
Classifier: Development Status :: 5 - Production/Stable
Classifier: Framework :: Plone
Classifier: License :: OSI Approved :: GNU General Public License v2 or later (GPLv2+)
Classifier: Programming Language :: Python
Classifier: Programming Language :: Python :: 3.7
Classifier: Programming Language :: Python :: 3.8
Classifier: Programming Language :: Python :: 3.9
Classifier: Programming Language :: Python :: 3.10
Classifier: Programming Language :: Python :: 3.11
Classifier: Programming Language :: Python :: 3.12
Requires-Python: >=3.7
Requires-Dist: setuptools
Requires-Dist: Products.GenericSetup
Requires-Dist: Products.MailHost
Requires-Dist: Products.CMFCore
Provides-Extra: test
Requires-Dist: plone.app.testing ; extra == 'test'
Requires-Dist: plone.testing ; extra == 'test'
Requires-Dist: zope.component ; extra == 'test'
